pyflunt/__init__.py
pyflunt/notifications.py
pyflunt/validations.py
pyflunt-1.0.0.dist-info/LICENSE
pyflunt-1.0.0.dist-info/METADATA
pyflunt-1.0.0.dist-info/WHEEL
pyflunt-1.0.0.dist-info/top_level.txt
pyflunt-1.0.0.dist-info/RECORD
