Metadata-Version: 2.1
Name: pyflunt
Version: 1.0.0
Summary: Python implementation of Domain Notification Pattern based in Flunt(.NET), JFlunt(Java) developed by @andrebaltieri, @carlosbritojun
Home-page: https://github.com/flaviogf/pyflunt/
Author: Flavio Fernandes
Author-email: flavio.fernandes6@gmail.com
License: UNKNOWN
Platform: UNKNOWN
